{
  "type": "Feature",
  "properties": {
    "gn:admin1_code":"0.0",
    "gn:asciiname":"Angoro",
    "gn:country_code":"YT",
    "gn:dem":390,
    "gn:feature_class":"P",
    "gn:feature_code":"PPL",
    "gn:name":"Angoro",
    "gn:population":0,
    "gn:timezone":"Indian/Mayotte",
    "iso:country":"YT",
    "name:und_x_variant":[
        "Angaro",
        "Angoro"
    ],
    "wof:name":"Angoro",
    "wof:placetype":"locality"
},
  "geometry": {"coordinates":[45.23333,-12.75],"type":"Point"}
}