{
  "type": "Feature",
  "properties": {
    "gn:admin1_code":"0.0",
    "gn:asciiname":"Tsoundzou Deux",
    "gn:country_code":"YT",
    "gn:dem":36,
    "gn:feature_class":"P",
    "gn:feature_code":"PPL",
    "gn:name":"Tsoundzou Deux",
    "gn:population":0,
    "gn:timezone":"Indian/Mayotte",
    "iso:country":"YT",
    "name:fra_x_preferred":[
        "Tsoundzou Deux"
    ],
    "wof:name":"Tsoundzou Deux",
    "wof:placetype":"locality"
},
  "geometry": {"coordinates":[45.1972,-12.81845],"type":"Point"}
}