{
  "type": "Feature",
  "properties": {
    "gn:admin1_code":"0.0",
    "gn:asciiname":"Majikavo Lamir",
    "gn:cc2":"YT",
    "gn:country_code":"YT",
    "gn:dem":29,
    "gn:feature_class":"P",
    "gn:feature_code":"PPL",
    "gn:name":"Majikavo Lamir",
    "gn:population":0,
    "gn:timezone":"Indian/Mayotte",
    "iso:country":"YT",
    "name:und_x_variant":[
        "Majikavo 1",
        "Majikavo Lamir"
    ],
    "wof:name":"Majikavo Lamir",
    "wof:placetype":"locality"
},
  "geometry": {"coordinates":[45.22968,-12.75572],"type":"Point"}
}