{
  "type": "Feature",
  "properties": {
    "gn:admin1_code":"0.0",
    "gn:asciiname":"Hamjago",
    "gn:country_code":"YT",
    "gn:dem":13,
    "gn:feature_class":"P",
    "gn:feature_code":"PPL",
    "gn:name":"Hamjago",
    "gn:population":0,
    "gn:timezone":"Indian/Mayotte",
    "iso:country":"YT",
    "wof:name":"Hamjago",
    "wof:placetype":"locality"
},
  "geometry": {"coordinates":[45.0745,-12.68832],"type":"Point"}
}