{
  "type": "Feature",
  "properties": {
    "gn:admin1_code":"0.0",
    "gn:asciiname":"Bouchini",
    "gn:country_code":"YT",
    "gn:dem":130,
    "gn:feature_class":"P",
    "gn:feature_code":"PPL",
    "gn:name":"Bouchini",
    "gn:population":0,
    "gn:timezone":"Indian/Mayotte",
    "iso:country":"YT",
    "name:fra_x_preferred":[
        "Bouchini"
    ],
    "wof:name":"Bouchini",
    "wof:placetype":"locality"
},
  "geometry": {"coordinates":[45.10527,-12.68996],"type":"Point"}
}