{
  "type": "Feature",
  "properties": {
    "gn:admin1_code":"0.0",
    "gn:asciiname":"Vahibe",
    "gn:country_code":"YT",
    "gn:dem":208,
    "gn:feature_class":"P",
    "gn:feature_code":"PPL",
    "gn:name":"Vahib\u00e9",
    "gn:population":0,
    "gn:timezone":"Indian/Mayotte",
    "iso:country":"YT",
    "name:fra_x_preferred":[
        "Vahib\u00e9"
    ],
    "name:und_x_variant":[
        "Vahib\u00e9ni"
    ],
    "wof:name":"Vahibe",
    "wof:placetype":"locality"
},
  "geometry": {"coordinates":[45.17707,-12.79024],"type":"Point"}
}