{
  "type": "Feature",
  "properties": {
    "gn:admin1_code":"0.0",
    "gn:asciiname":"Combani",
    "gn:country_code":"YT",
    "gn:dem":129,
    "gn:feature_class":"P",
    "gn:feature_code":"PPL",
    "gn:name":"Combani",
    "gn:population":0,
    "gn:timezone":"Indian/Mayotte",
    "iso:country":"YT",
    "name:fra_x_preferred":[
        "Combani"
    ],
    "wof:name":"Combani",
    "wof:placetype":"locality"
},
  "geometry": {"coordinates":[45.13405,-12.78802],"type":"Point"}
}