{
  "type": "Feature",
  "properties": {
    "gn:admin1_code":"0.0",
    "gn:asciiname":"Kavani",
    "gn:country_code":"YT",
    "gn:dem":26,
    "gn:feature_class":"P",
    "gn:feature_code":"PPL",
    "gn:name":"Kavani",
    "gn:population":0,
    "gn:timezone":"Indian/Mayotte",
    "iso:country":"YT",
    "name:fra_x_preferred":[
        "Kavani"
    ],
    "wof:name":"Kavani",
    "wof:placetype":"locality"
},
  "geometry": {"coordinates":[45.19564,-12.91497],"type":"Point"}
}