{
  "type": "Feature",
  "properties": {
    "gn:admin1_code":"0.0",
    "gn:asciiname":"Mbouanasta",
    "gn:country_code":"YT",
    "gn:dem":13,
    "gn:feature_class":"P",
    "gn:feature_code":"PPL",
    "gn:name":"Mbouanasta",
    "gn:population":0,
    "gn:timezone":"Indian/Mayotte",
    "iso:country":"YT",
    "name:fra_x_preferred":[
        "Mbouanasta"
    ],
    "name:und_x_variant":[
        "Mbou\u00e9anatsa"
    ],
    "wof:name":"Mbouanasta",
    "wof:placetype":"locality"
},
  "geometry": {"coordinates":[45.102,-12.94433],"type":"Point"}
}