{
  "type": "Feature",
  "properties": {
    "gn:admin1_code":"0.0",
    "gn:asciiname":"Saziley",
    "gn:country_code":"YT",
    "gn:dem":18,
    "gn:feature_class":"P",
    "gn:feature_code":"PPL",
    "gn:name":"Saziley",
    "gn:population":0,
    "gn:timezone":"Indian/Mayotte",
    "iso:country":"YT",
    "name:fra_x_preferred":[
        "Saziley"
    ],
    "name:und_x_variant":[
        "Sazil\u00e9"
    ],
    "wof:name":"Saziley",
    "wof:placetype":"locality"
},
  "geometry": {"coordinates":[45.18119,-12.98436],"type":"Point"}
}