{
  "type": "Feature",
  "properties": {
    "gn:admin1_code":"0.0",
    "gn:asciiname":"Sohoa",
    "gn:country_code":"YT",
    "gn:dem":37,
    "gn:feature_class":"P",
    "gn:feature_code":"PPL",
    "gn:name":"Sohoa",
    "gn:population":0,
    "gn:timezone":"Indian/Mayotte",
    "iso:country":"YT",
    "wof:name":"Sohoa",
    "wof:placetype":"locality"
},
  "geometry": {"coordinates":[45.10552,-12.82233],"type":"Point"}
}