{
  "type": "Feature",
  "properties": {
    "gn:admin1_code":"0.0",
    "gn:asciiname":"Mrereni Be",
    "gn:country_code":"YT",
    "gn:dem":33,
    "gn:feature_class":"P",
    "gn:feature_code":"PPL",
    "gn:name":"Mr\u00e9r\u00e9ni B\u00e9",
    "gn:population":0,
    "gn:timezone":"Indian/Mayotte",
    "iso:country":"YT",
    "name:fra_x_preferred":[
        "Mr\u00e9r\u00e9ni B\u00e9"
    ],
    "wof:name":"Mrereni Be",
    "wof:placetype":"locality"
},
  "geometry": {"coordinates":[45.15524,-12.9058],"type":"Point"}
}